[
{
    "condition": "minecraft:inverted",
    "term": {
  "condition": "minecraft:entity_properties",
  "entity": "this",
  "predicate": {
    "equipment": {
      "mainhand": {
        "tag": "dynamic_lights_by_creepermeyt:lightlvl_15"
      }
    }
  }
}
},
{
    "condition": "minecraft:inverted",
    "term": {
  "condition": "minecraft:entity_properties",
  "entity": "this",
  "predicate": {
    "equipment": {
      "offhand": {
        "tag": "dynamic_lights_by_creepermeyt:lightlvl_15"
      }
    }
  }
}
}
]
